<?xml version="1.0" encoding="UTF-8"?><?xml-stylesheet type='text/xsl' href='_UpgradeReport_Files/UpgradeReport.xslt'?><UpgradeLog>
<Properties><Property Name="Solution" Value="SPH">
</Property><Property Name="Solution File" Value="C:\Users\Lakshmi\Documents\GitHub\SPH_Simulation\fluids_v2\SPH\SPH.sln">
</Property><Property Name="Date" Value="Wednesday, March 5, 2014">
</Property><Property Name="Time" Value="20:29:22 PM">
</Property></Properties><Event ErrorLevel="0" Project="fluids" Source="..\fluids_v2\fluids.vcproj" Description="Converting project file 'C:\Users\Lakshmi\Documents\GitHub\SPH_Simulation\fluids_v2\fluids_v2\fluids.vcproj'.">
</Event><Event ErrorLevel="1" Project="fluids" Source="..\fluids_v2\fluids.vcproj" Description="VCWebServiceProxyGeneratorTool is no longer supported. The tool has been removed from your project settings.">
</Event><Event ErrorLevel="1" Project="fluids" Source="..\fluids_v2\fluids.vcproj" Description="Attribute 'Detect64BitPortabilityProblems' of 'VCCLCompilerTool' is not supported in this version and has been removed during conversion.">
</Event><Event ErrorLevel="1" Project="fluids" Source="..\fluids_v2\fluids.vcproj" Description="Attribute 'Detect64BitPortabilityProblems' of 'VCCLCompilerTool' is not supported in this version and has been removed during conversion.">
</Event><Event ErrorLevel="1" Project="fluids" Source="..\fluids_v2\fluids.vcproj" Description="MSB8012: $(TargetName) ('fluids') does not match the Linker's OutputFile property value 'C:\Users\Lakshmi\Documents\GitHub\SPH_Simulation\fluids_v2\SPH\Debug\fluids_debug.exe' ('fluids_debug') in project configuration 'Debug|Win32'. This may cause your project to build incorrectly. To correct this, please make sure that $(TargetName) property value matches the value specified in %(Link.OutputFile).">
</Event><Event ErrorLevel="1" Project="fluids" Source="..\fluids_v2\fluids.vcproj" Description="MSB8012: $(TargetPath) ('C:\Users\Lakshmi\Documents\GitHub\SPH_Simulation\fluids_v2\SPH\Debug\fluids.exe') does not match the Linker's OutputFile property value 'C:\Users\Lakshmi\Documents\GitHub\SPH_Simulation\fluids_v2\SPH\Debug\fluids_debug.exe' ('C:\Users\Lakshmi\Documents\GitHub\SPH_Simulation\fluids_v2\SPH\Debug\fluids_debug.exe') in project configuration 'Debug|Win32'. This may cause your project to build incorrectly. To correct this, please make sure that $(TargetPath) property value matches the value specified in %(Link.OutputFile).">
</Event><Event ErrorLevel="1" Project="fluids" Source="..\fluids_v2\fluids.vcproj" Description="MSB8012: $(TargetPath) ('C:\Users\Lakshmi\Documents\GitHub\SPH_Simulation\fluids_v2\fluids_v2\Release\fluids.exe') does not match the Linker's OutputFile property value 'Release\fluids.exe' ('C:\Users\Lakshmi\Documents\GitHub\SPH_Simulation\fluids_v2\SPH\Release\fluids.exe') in project configuration 'Release|Win32'. This may cause your project to build incorrectly. To correct this, please make sure that $(TargetPath) property value matches the value specified in %(Link.OutputFile).">
</Event><Event ErrorLevel="0" Project="fluids" Source="..\fluids_v2\fluids.vcproj" Description="Done converting to new project file 'C:\Users\Lakshmi\Documents\GitHub\SPH_Simulation\fluids_v2\fluids_v2\fluids.vcxproj'.">
</Event><Event ErrorLevel="3" Project="fluids" Source="..\fluids_v2\fluids.vcproj" Description="Converted">
</Event><Event ErrorLevel="2" Project="" Source="..\fluids_v2\fluids.vcxproj" Description="">
</Event></UpgradeLog>